[
  {
    "singer": "DJ Khaled",
    "track": "I Got The Keys",
    "words": 17
  },
  {
    "singer": "Jay-Z",
    "track": "I Got The Keys",
    "words": 256
  },
  {
    "singer": "Future",
    "track": "I Got The Keys",
    "words": 320
  },
  {
    "singer": "DJ Khaled",
    "track": "For Free",
    "words": 54
  },
  {
    "singer": "Drake",
    "track": "For Free",
    "words": 325
  },
  {
    "singer": "DJ Khaled",
    "track": "Nas Album Done",
    "words": 11
  },
  {
    "singer": "Nas",
    "track": "Nas Album Done",
    "words": 398
  },
  {
    "singer": "DJ Khaled",
    "track": "Holy Key",
    "words": 56
  },
  {
    "singer": "Big Sean",
    "track": "Holy Key",
    "words": 159
  },
  {
    "singer": "Kendrick Lamar",
    "track": "Holy Key",
    "words": 284
  },
  {
    "singer": "Betty Wright",
    "track": "Holy Key",
    "words": 106
  },
  {
    "singer": "EarthGang",
    "track": "Jermaine's Interlude",
    "words": 92
  },
  {
    "singer": "J.Cole",
    "track": "Jermaine's Interlude",
    "words": 292
  },
  {
    "singer": "DJ Khaled",
    "track": "Ima Be Alright",
    "words": 47
  },
  {
    "singer": "Future",
    "track": "Ima Be Alright",
    "words": 145
  },
  {
    "singer": "Bryson Tiller",
    "track": "Ima Be Alright",
    "words": 397
  },
  {
    "singer": "DJ Khaled",
    "track": "Do You Mind",
    "words": 7
  },
  {
    "singer": "Nicki Minaj",
    "track": "Do You Mind",
    "words": 108
  },
  {
    "singer": "Chris Brown",
    "track": "Do You Mind",
    "words": 347
  },
  {
    "singer": "Future",
    "track": "Do You Mind",
    "words": 78
  },
  {
    "singer": "Jeremih",
    "track": "Do You Mind",
    "words": 63
  },
  {
    "singer": "August Alsina",
    "track": "Do You Mind",
    "words": 154
  },
  {
    "singer": "Rick Ross",
    "track": "Do You Mind",
    "words": 68
  },
  {
    "singer": "DJ Khaled",
    "track": "Pick These Hoes Apart",
    "words": 3
  },
  {
    "singer": "Kodak Black",
    "track": "Pick These Hoes Apart",
    "words": 144
  },
  {
    "singer": "Jeezy",
    "track": "Pick These Hoes Apart",
    "words": 302
  },
  {
    "singer": "French Montana",
    "track": "Pick These Hoes Apart",
    "words": 130
  },
  {
    "singer": "DJ Khaled",
    "track": "Fuck Up The Club",
    "words": 2
  },
  {
    "singer": "Future",
    "track": "Fuck Up The Club",
    "words": 356
  },
  {
    "singer": "Rick Ross",
    "track": "Fuck Up The Club",
    "words": 109
  },
  {
    "singer": "YG",
    "track": "Fuck Up The Club",
    "words": 95
  },
  {
    "singer": "Yo Gotti",
    "track": "Fuck Up The Club",
    "words": 120
  },
  {
    "singer": "DJ Khaled",
    "track": "Work For It",
    "words": 2
  },
  {
    "singer": "Big Sean",
    "track": "Work For It",
    "words": 148
  },
  {
    "singer": "Gucci Mane",
    "track": "Work For It",
    "words": 90
  },
  {
    "singer": "2 Chainz",
    "track": "Work For It",
    "words": 56
  },
  {
    "singer": "DJ Khaled",
    "track": "Don't Ever Play Yourself",
    "words": 2
  },
  {
    "singer": "Jadakiss",
    "track": "Don't Ever Play Yourself",
    "words": 196
  },
  {
    "singer": "Fabolous",
    "track": "Don't Ever Play Yourself",
    "words": 175
  },
  {
    "singer": "Busta Rhymes",
    "track": "Don't Ever Play Yourself",
    "words": 222
  },
  {
    "singer": "Fat Joe",
    "track": "Don't Ever Play Yourself",
    "words": 123
  },
  {
    "singer": "Kent Jones",
    "track": "Don't Ever Play Yourself",
    "words": 330
  },
  {
    "singer": "DJ Khaled",
    "track": "Tourist",
    "words": 6
  },
  {
    "singer": "Travis Scott",
    "track": "Tourist",
    "words": 353
  },
  {
    "singer": "Lil Wayne",
    "track": "Tourist",
    "words": 128
  },
  {
    "singer": "DJ Khaled",
    "track": "Forgive Me Father",
    "words": 3
  },
  {
    "singer": "Meghan Trainor",
    "track": "Forgive Me Father",
    "words": 114
  },
  {
    "singer": "Wiz Khalifa",
    "track": "Forgive Me Father",
    "words": 177
  },
  {
    "singer": "Wale",
    "track": "Forgive Me Father",
    "words": 89
  },
  {
    "singer": "Mavado",
    "track": "Progress",
    "words": 353
  }
]